[
  {
      "startdate": [
          "03.05.2020"
      ],
      "enddate": [
          "03.05.2020"
      ],
      "time": [
          "14:00 til 14:30"
      ],
      "place-name": "\n  Kulturhuset Islands Brygge",
      "place-address": [
          ""
      ],
      "place-phone": "",
      "place-country": "Denmark",
      "place-url": [
          ""
      ],
      "place-category": [],
      "place-email": [
          ""
      ],
      "image": "https://kulturhusetislandsbrygge.kk.dk/sites/kulturhusetislandsbrygge.kk.dk/files/uploaded-images/papkas1.jpg",
      "Linkydinky": "<a href=\"https://kulturhusetislandsbrygge.kk.dk/event/teater-de-helt-smaa-pap-kas\">vis</a>",
      "UUID": "90c60b1b-f16b-492e-b7f8-184d18911852",
      "Nid": "5020",
      "Sti": "/event/teater-de-helt-smaa-pap-kas",
      "title": "Teater for de helt små: [pAp]-[kAs]",
      "field_teaser": "Sanseligt teater med kæmpestore og bittesmå papkasser.",
      "body": "pAp-kAsser er ikke kun pAp-kAsser – de kan skabe verdener! Ro af sted i bølgegang og salt havvind, og oplev en frodig skov af træer vokse frem for øjnene af dig, før den i ét nu forvandles til et nyt landskab. Gem dig i kæmpestore pAp-kAsser, eller byg med bittesmå pAp-kAsseklodser – men hold øje med den drilske legekammerats forsøg på at vælte tårnet!&nbsp; Understøttet af sanselig musik og spillernes nærværende kontakt til publikum tilbyder [pAp]-[kAs] vores mindste verdensborgere en kvalitetsoplevelse, der stimulerer hele sanseapparatet og minder deres voksne om legens vigtighed for vores forståelse af verden.\r\n\r\nFor 1,5-3 år&nbsp;\r\n\r\nForestillingen spiller kl. 14&nbsp;(klik her for billet) og kl. 15&nbsp;(klik her for billet)\r\n",
      "field_price": "40 kr.",
      "Ticket sale": "https://billetto.dk/e/pap-kas-af-hvid-stoj-billetter-401076/",
      "field_display_list": [
          ""
      ],
      "field_display_institution": "",
      "field_free_tekst": ""
  },
  {
      "startdate": [
          "18.04.2020"
      ],
      "enddate": [
          "18.04.2020"
      ],
      "time": [
          "15:00 til 15:40"
      ],
      "place-name": "\n  Kulturhuset Islands Brygge",
      "place-address": [
          ""
      ],
      "place-phone": "",
      "place-country": "Denmark",
      "place-url": [
          ""
      ],
      "place-category": [],
      "place-email": [
          ""
      ],
      "image": "https://kulturhusetislandsbrygge.kk.dk/sites/kulturhusetislandsbrygge.kk.dk/files/uploaded-images/palle_web.jpg",
      "Linkydinky": "<a href=\"https://kulturhusetislandsbrygge.kk.dk/event/teater-boern-palle-p-og-perlen\">vis</a>",
      "UUID": "2cff21c4-741f-47c0-a809-9069c85a0943",
      "Nid": "5019",
      "Sti": "/event/teater-boern-palle-p-og-perlen",
      "title": "Teater for børn: Palle P og Perlen",
      "field_teaser": "Hvad gør man, når man er så glad for noget, at man bliver bange for at miste det igen?",
      "body": "Palle P ønsker sig så meget at finde noget værdifuldt, noget vigtigt, noget at holde af. En dag finder han ved et tilfælde en meget stor og smuk perle. Han bliver lykkelig, faktisk er han verdens lykkeligste dreng. Men da det bliver aften, bliver han bange for, at han skal miste perlen.\r\nEn forestilling om drømme og angsten for at miste. Om oprustning og venskab. En lille perle frit efter Marianne Iben Hansen og Jon Ranheimsæters børnebog.\r\n\r\nFra 4 år.&nbsp;\r\n",
      "field_price": "40 kr.",
      "Ticket sale": "https://billetto.dk/e/palle-p-og-perlen-af-norregaards-teater-billetter-401066/",
      "field_display_list": [
          ""
      ],
      "field_display_institution": "",
      "field_free_tekst": ""
  },
  {
      "startdate": [
          "04.04.2020"
      ],
      "enddate": [
          "04.04.2020"
      ],
      "time": [
          "15:00 til 15:30"
      ],
      "place-name": "\n  Kulturhuset Islands Brygge",
      "place-address": [
          ""
      ],
      "place-phone": "",
      "place-country": "Denmark",
      "place-url": [
          ""
      ],
      "place-category": [],
      "place-email": [
          ""
      ],
      "image": "https://kulturhusetislandsbrygge.kk.dk/sites/kulturhusetislandsbrygge.kk.dk/files/uploaded-images/4_4_vred4.jpg",
      "Linkydinky": "<a href=\"https://kulturhusetislandsbrygge.kk.dk/event/vred-en-boerneforestilling-om-vrede\">vis</a>",
      "UUID": "fdcabc86-1c6d-4893-b0e6-b71c7706bf6f",
      "Nid": "5018",
      "Sti": "/event/vred-en-boerneforestilling-om-vrede",
      "title": "VRED - en børneforestilling om vrede",
      "field_teaser": "I en sjov, nonverbal stil, inspireret af børnenes eget univers, undersøger vi vredens væsen. ",
      "body": "”Jeg er sur i dag! Vred! Rasende! Det hele er bare dumt-dumt-dumt!!!\r\n\r\nI en sjov, nonverbal stil, inspireret af børnenes eget univers, undersøger vi vredens væsen. Hvorfor bliver man vred? Er det okay at blive vred? Kan man bruge vrede til noget, og hvordan bliver man glad igen?\r\nForestillingen, der er opbygget af flere forskellige sekvenser, udspiller sig i en på én gang enkel og magisk verden, hvor alt er muligt – det sjove, det poetiske, det overraskende, det stille, det voldsomme, det musikalske og det legende. Der bliver masser at snakke om efterfølgende for børn i alle aldre.\r\n",
      "field_price": "40 kr.",
      "Ticket sale": "https://billetto.dk/e/vred-af-limfjordsteatret-billetter-401064/",
      "field_display_list": [
          ""
      ],
      "field_display_institution": "",
      "field_free_tekst": ""
  },
  {
      "startdate": [
          "29.02.2020"
      ],
      "enddate": [
          "29.02.2020"
      ],
      "time": [
          "13:00 til 14:00"
      ],
      "place-name": "\n  Kulturhuset Islands Brygge",
      "place-address": [
          ""
      ],
      "place-phone": "",
      "place-country": "Denmark",
      "place-url": [
          ""
      ],
      "place-category": [],
      "place-email": [
          ""
      ],
      "image": "https://kulturhusetislandsbrygge.kk.dk/sites/kulturhusetislandsbrygge.kk.dk/files/uploaded-images/29_2_nat_i_mali.jpg",
      "Linkydinky": "<a href=\"https://kulturhusetislandsbrygge.kk.dk/event/familiekoncert-nat-i-mali\">vis</a>",
      "UUID": "6b0fca35-d623-4d23-9206-6635353f574a",
      "Nid": "5017",
      "Sti": "/event/familiekoncert-nat-i-mali",
      "title": "Familiekoncert: Nat i Mali",
      "field_teaser": "Moussa Diallo digter videre på en række af sin barndoms underfundige fortællinger.",
      "body": "Det er nat i Mali. Stjerner og måne oplyser himlen, og i landsbyen Koulikoro får børnene fortalt eventyr om den tapre mariehøne Kimi Komo, om hanen Karato og firbenet Kanou og om den farlige løve, der vist godt kunne spise en lille ged.&nbsp;\r\n\r\nMoussa Diallo, der i årenes løb, har spillet et hav af koncerter for børn, digter videre på en række af sin barndoms underfundige fortællinger og genskaber den magiske stemning, som han selv oplevede, når de ældste i landsbyen fortalte eventyr.\r\nMedvirkende: Moussa Diallo (fortæller, vokal, bas), Preben Carlsen (guitar) og Tea Bendix (tegner).\r\n\r\nFor 3-8 år&nbsp;\r\n",
      "field_price": "60 kr.",
      "Ticket sale": "https://billetto.dk/e/familiekoncert-nat-i-mali-billetter-400836/",
      "field_display_list": [
          ""
      ],
      "field_display_institution": "",
      "field_free_tekst": ""
  },
  {
      "startdate": [
          "21.03.2020"
      ],
      "enddate": [
          "21.03.2020"
      ],
      "time": [
          "13:00 til 14:00"
      ],
      "place-name": "\n  Kulturhuset Islands Brygge",
      "place-address": [
          ""
      ],
      "place-phone": "",
      "place-country": "Denmark",
      "place-url": [
          ""
      ],
      "place-category": [],
      "place-email": [
          ""
      ],
      "image": "https://kulturhusetislandsbrygge.kk.dk/sites/kulturhusetislandsbrygge.kk.dk/files/uploaded-images/21_3_min_mormors_gebis.jpg",
      "Linkydinky": "<a href=\"https://kulturhusetislandsbrygge.kk.dk/event/familiekoncert-min-mormors-gebis-med-dissing-las\">vis</a>",
      "UUID": "b7a55a70-ca37-4941-90d3-2f050fef3434",
      "Nid": "5009",
      "Sti": "/event/familiekoncert-min-mormors-gebis-med-dissing-las",
      "title": "Familiekoncert: Min mormors gebis med Dissing &amp; Las",
      "field_teaser": "Jacob Martin Strids bestseller-børnebog tilsat reggae, rock, folk og rendyrket pop",
      "body": "Der er frække numre, eftertænksomme numre og numre spækket med detaljer og finurlige reallyde.&nbsp;Min mormors gebis&nbsp;er en musikalsk fortolkning af Jakob Martin Strids bestseller-børnebog af samme navn. Og fordi bogen sprudler, gør trioen det samme. Koncerten&nbsp;spænder fra folk og rock over reggae til rendyrket pop.\r\n\r\n- Kigger man på bogens tegninger, bliver man let inspireret til at flippe ud i alle mulige retninger. Og vi har ladet os drive med. En del børneplader lyder lidt som om, de er tilpasset at skulle køre i baggrunden uden at genere nogen. Men vi har ønsket at nå dertil, hvor det blev en fælles oplevelse for børn og voksne, ligesom bogen. Vi har tænkt: ’Hvad ville Jakob synes om det her?’ Sangene skulle have noget af hans anarki, så det er blevet et børnealbum med&nbsp;horn i panden.&nbsp;\r\n\r\n\r\nBogens afsæt kom, da Jakob Martin Strid over hals og hoved bad trioen om at sætte musik til en tekst i forbindelse med, at han fik Kronprinsparrets Kulturpris. Dissing &amp; Las lavede ’Grønlands is’, og alle var så glade for resultatet, at samarbejdet blev udvidet til at omfatte hele den bramfri bog om medisterminister Fister, om et araberkomplot mod en rabarberkompot og om hvaler i Holmens Kanal.\r\n\r\nFra&nbsp;5-10 år\r\n",
      "field_price": "60 kr. pr. person",
      "Ticket sale": "https://billetto.dk/e/familiekoncert-min-mormors-gebis-med-dissing-las-billetter-401061/",
      "field_display_list": [
          "\n  \n    kib_screen02  \n"
      ],
      "field_display_institution": "",
      "field_free_tekst": ""
  }
]
